{
  "_index": [
    "COLUMNNAME"
  ],
  "added": [
    {
      "COLUMNNAME": "ADRLN1",
      "DATATYPE": "VARCHAR2",
      "LAYOUTID": "1196"
    },
    {
      "COLUMNNAME": "ADRLN2",
      "DATATYPE": "VARCHAR2",
      "LAYOUTID": "1196"
    },
    {
      "COLUMNNAME": "AREACD",
      "DATATYPE": "VARCHAR2",
      "LAYOUTID": "1196"
    },
    {
      "COLUMNNAME": "BTHDAT",
      "DATATYPE": "DATE",
      "LAYOUTID": "1196"
    },
    {
      "COLUMNNAME": "CASEHD",
      "DATATYPE": "VARCHAR2",
      "LAYOUTID": "1196"
    },
    {
      "COLUMNNAME": "CHADRLN1",
      "DATATYPE": "VARCHAR2",
      "LAYOUTID": "1196"
    },
    {
      "COLUMNNAME": "CHADRLN2",
      "DATATYPE": "VARCHAR2",
      "LAYOUTID": "1196"
    },
    {
      "COLUMNNAME": "CHCITY",
      "DATATYPE": "VARCHAR2",
      "LAYOUTID": "1196"
    },
    {
      "COLUMNNAME": "CHFSTNAM",
      "DATATYPE": "VARCHAR2",
      "LAYOUTID": "1196"
    },
    {
      "COLUMNNAME": "CHLSTNAM",
      "DATATYPE": "VARCHAR2",
      "LAYOUTID": "1196"
    },
    {
      "COLUMNNAME": "CHSTATE",
      "DATATYPE": "VARCHAR2",
      "LAYOUTID": "1196"
    },
    {
      "COLUMNNAME": "CHZIP",
      "DATATYPE": "VARCHAR2",
      "LAYOUTID": "1196"
    },
    {
      "COLUMNNAME": "CITYCD",
      "DATATYPE": "VARCHAR2",
      "LAYOUTID": "1196"
    },
    {
      "COLUMNNAME": "EFFDAT",
      "DATATYPE": "DATE",
      "LAYOUTID": "1196"
    },
    {
      "COLUMNNAME": "EXPDAT",
      "DATATYPE": "DATE",
      "LAYOUTID": "1196"
    },
    {
      "COLUMNNAME": "FSTNAM",
      "DATATYPE": "VARCHAR2",
      "LAYOUTID": "1196"
    },
    {
      "COLUMNNAME": "GRPNUM",
      "DATATYPE": "VARCHAR2",
      "LAYOUTID": "1196"
    },
    {
      "COLUMNNAME": "HMOID",
      "DATATYPE": "VARCHAR2",
      "LAYOUTID": "1196"
    },
    {
      "COLUMNNAME": "HOMPH",
      "DATATYPE": "VARCHAR2",
      "LAYOUTID": "1196"
    },
    {
      "COLUMNNAME": "LSTNAM",
      "DATATYPE": "VARCHAR2",
      "LAYOUTID": "1196"
    },
    {
      "COLUMNNAME": "MEMBNO",
      "DATATYPE": "VARCHAR2",
      "LAYOUTID": "1196"
    },
    {
      "COLUMNNAME": "MIDNAM",
      "DATATYPE": "VARCHAR2",
      "LAYOUTID": "1196"
    },
    {
      "COLUMNNAME": "PLANDESC",
      "DATATYPE": "VARCHAR2",
      "LAYOUTID": "1196"
    },
    {
      "COLUMNNAME": "PROVNO",
      "DATATYPE": "VARCHAR2",
      "LAYOUTID": "1196"
    },
    {
      "COLUMNNAME": "SEXCD",
      "DATATYPE": "VARCHAR2",
      "LAYOUTID": "1196"
    },
    {
      "COLUMNNAME": "SOCSEC",
      "DATATYPE": "VARCHAR2",
      "LAYOUTID": "1196"
    },
    {
      "COLUMNNAME": "STACOD",
      "DATATYPE": "VARCHAR2",
      "LAYOUTID": "1196"
    },
    {
      "COLUMNNAME": "TIERCD",
      "DATATYPE": "VARCHAR2",
      "LAYOUTID": "1196"
    },
    {
      "COLUMNNAME": "ZIPCOD",
      "DATATYPE": "VARCHAR2",
      "LAYOUTID": "1196"
    }
  ],
  "changed": [],
  "removed": [
    {
      "COLUMNNAME": "ADDR1",
      "DATATYPE": "VARCHAR2",
      "LAYOUTID": "42"
    },
    {
      "COLUMNNAME": "ADDR2",
      "DATATYPE": "VARCHAR2",
      "LAYOUTID": "42"
    },
    {
      "COLUMNNAME": "CITY",
      "DATATYPE": "VARCHAR2",
      "LAYOUTID": "42"
    },
    {
      "COLUMNNAME": "CMSTATUS",
      "DATATYPE": "VARCHAR2",
      "LAYOUTID": "42"
    },
    {
      "COLUMNNAME": "COVTYPEDESC",
      "DATATYPE": "VARCHAR2",
      "LAYOUTID": "42"
    },
    {
      "COLUMNNAME": "COVTYPEID",
      "DATATYPE": "VARCHAR2",
      "LAYOUTID": "42"
    },
    {
      "COLUMNNAME": "DATABEGINDATE",
      "DATATYPE": "DATE",
      "LAYOUTID": "42"
    },
    {
      "COLUMNNAME": "DATAENDDATE",
      "DATATYPE": "DATE",
      "LAYOUTID": "42"
    },
    {
      "COLUMNNAME": "DOB",
      "DATATYPE": "DATE",
      "LAYOUTID": "42"
    },
    {
      "COLUMNNAME": "EFFDATE",
      "DATATYPE": "DATE",
      "LAYOUTID": "42"
    },
    {
      "COLUMNNAME": "EMPLOYEECOUNT",
      "DATATYPE": "NUMBER",
      "LAYOUTID": "42"
    },
    {
      "COLUMNNAME": "ENRID",
      "DATATYPE": "VARCHAR2",
      "LAYOUTID": "42"
    },
    {
      "COLUMNNAME": "GENDER",
      "DATATYPE": "VARCHAR2",
      "LAYOUTID": "42"
    },
    {
      "COLUMNNAME": "HOMEPHONE",
      "DATATYPE": "VARCHAR2",
      "LAYOUTID": "42"
    },
    {
      "COLUMNNAME": "LOCATIONCODE",
      "DATATYPE": "VARCHAR2",
      "LAYOUTID": "42"
    },
    {
      "COLUMNNAME": "MEMBERCOUNT",
      "DATATYPE": "NUMBER",
      "LAYOUTID": "42"
    },
    {
      "COLUMNNAME": "MEMFIRSTNAME",
      "DATATYPE": "VARCHAR2",
      "LAYOUTID": "42"
    },
    {
      "COLUMNNAME": "MEMID",
      "DATATYPE": "VARCHAR2",
      "LAYOUTID": "42"
    },
    {
      "COLUMNNAME": "MEMLASTNAME",
      "DATATYPE": "VARCHAR2",
      "LAYOUTID": "42"
    },
    {
      "COLUMNNAME": "PARTTIMEFULLTIMEINDICATOR",
      "DATATYPE": "VARCHAR2",
      "LAYOUTID": "42"
    },
    {
      "COLUMNNAME": "PCPID",
      "DATATYPE": "VARCHAR2",
      "LAYOUTID": "42"
    },
    {
      "COLUMNNAME": "PCPNAME",
      "DATATYPE": "VARCHAR2",
      "LAYOUTID": "42"
    },
    {
      "COLUMNNAME": "PLANNAME",
      "DATATYPE": "VARCHAR2",
      "LAYOUTID": "42"
    },
    {
      "COLUMNNAME": "PLANTYPE",
      "DATATYPE": "VARCHAR2",
      "LAYOUTID": "42"
    },
    {
      "COLUMNNAME": "RECORDCOUNT",
      "DATATYPE": "NUMBER",
      "LAYOUTID": "42"
    },
    {
      "COLUMNNAME": "RELFLAG",
      "DATATYPE": "VARCHAR2",
      "LAYOUTID": "42"
    },
    {
      "COLUMNNAME": "STATE",
      "DATATYPE": "VARCHAR2",
      "LAYOUTID": "42"
    },
    {
      "COLUMNNAME": "STATUS",
      "DATATYPE": "VARCHAR2",
      "LAYOUTID": "42"
    },
    {
      "COLUMNNAME": "TERMDATE",
      "DATATYPE": "DATE",
      "LAYOUTID": "42"
    },
    {
      "COLUMNNAME": "WORKPHONE",
      "DATATYPE": "VARCHAR2",
      "LAYOUTID": "42"
    },
    {
      "COLUMNNAME": "ZIP",
      "DATATYPE": "VARCHAR2",
      "LAYOUTID": "42"
    }
  ]
}