{
  "_index": [
    "COLUMNNAME"
  ],
  "added": [
    {
      "COLUMNNAME": "Acct",
      "DATATYPE": "VARCHAR2",
      "LAYOUTID": "1101"
    },
    {
      "COLUMNNAME": "DRUCov",
      "DATATYPE": "VARCHAR2",
      "LAYOUTID": "1101"
    },
    {
      "COLUMNNAME": "DRUNetworks",
      "DATATYPE": "VARCHAR2",
      "LAYOUTID": "1101"
    },
    {
      "COLUMNNAME": "DentalCoverage",
      "DATATYPE": "VARCHAR2",
      "LAYOUTID": "1101"
    },
    {
      "COLUMNNAME": "DentalNetworks",
      "DATATYPE": "VARCHAR2",
      "LAYOUTID": "1101"
    },
    {
      "COLUMNNAME": "DepID",
      "DATATYPE": "VARCHAR2",
      "LAYOUTID": "1101"
    },
    {
      "COLUMNNAME": "Dept",
      "DATATYPE": "VARCHAR2",
      "LAYOUTID": "1101"
    },
    {
      "COLUMNNAME": "Div",
      "DATATYPE": "VARCHAR2",
      "LAYOUTID": "1101"
    },
    {
      "COLUMNNAME": "EmployeeName",
      "DATATYPE": "VARCHAR2",
      "LAYOUTID": "1101"
    },
    {
      "COLUMNNAME": "FirstName",
      "DATATYPE": "VARCHAR2",
      "LAYOUTID": "1101"
    },
    {
      "COLUMNNAME": "Gender",
      "DATATYPE": "VARCHAR2",
      "LAYOUTID": "1101"
    },
    {
      "COLUMNNAME": "GroupName",
      "DATATYPE": "VARCHAR2",
      "LAYOUTID": "1101"
    },
    {
      "COLUMNNAME": "Grp",
      "DATATYPE": "VARCHAR2",
      "LAYOUTID": "1101"
    },
    {
      "COLUMNNAME": "IID",
      "DATATYPE": "VARCHAR2",
      "LAYOUTID": "1101"
    },
    {
      "COLUMNNAME": "LastName",
      "DATATYPE": "VARCHAR2",
      "LAYOUTID": "1101"
    },
    {
      "COLUMNNAME": "MI",
      "DATATYPE": "VARCHAR2",
      "LAYOUTID": "1101"
    },
    {
      "COLUMNNAME": "MedicalCoverage",
      "DATATYPE": "VARCHAR2",
      "LAYOUTID": "1101"
    },
    {
      "COLUMNNAME": "MedicalNetworks",
      "DATATYPE": "VARCHAR2",
      "LAYOUTID": "1101"
    },
    {
      "COLUMNNAME": "Plan",
      "DATATYPE": "VARCHAR2",
      "LAYOUTID": "1101"
    },
    {
      "COLUMNNAME": "RelToEE",
      "DATATYPE": "VARCHAR2",
      "LAYOUTID": "1101"
    },
    {
      "COLUMNNAME": "SSN",
      "DATATYPE": "VARCHAR2",
      "LAYOUTID": "1101"
    },
    {
      "COLUMNNAME": "STDCoverage",
      "DATATYPE": "VARCHAR2",
      "LAYOUTID": "1101"
    },
    {
      "COLUMNNAME": "VisionCoverage",
      "DATATYPE": "VARCHAR2",
      "LAYOUTID": "1101"
    },
    {
      "COLUMNNAME": "VisionNetworks",
      "DATATYPE": "VARCHAR2",
      "LAYOUTID": "1101"
    }
  ],
  "changed": [
    {
      "fields": {
        "LAYOUTID": {
          "from": "42",
          "to": "1101"
        }
      },
      "key": [
        "DOB"
      ]
    }
  ],
  "removed": [
    {
      "COLUMNNAME": "ADDR1",
      "DATATYPE": "VARCHAR2",
      "LAYOUTID": "42"
    },
    {
      "COLUMNNAME": "ADDR2",
      "DATATYPE": "VARCHAR2",
      "LAYOUTID": "42"
    },
    {
      "COLUMNNAME": "CITY",
      "DATATYPE": "VARCHAR2",
      "LAYOUTID": "42"
    },
    {
      "COLUMNNAME": "CMSTATUS",
      "DATATYPE": "VARCHAR2",
      "LAYOUTID": "42"
    },
    {
      "COLUMNNAME": "COVTYPEDESC",
      "DATATYPE": "VARCHAR2",
      "LAYOUTID": "42"
    },
    {
      "COLUMNNAME": "COVTYPEID",
      "DATATYPE": "VARCHAR2",
      "LAYOUTID": "42"
    },
    {
      "COLUMNNAME": "DATABEGINDATE",
      "DATATYPE": "DATE",
      "LAYOUTID": "42"
    },
    {
      "COLUMNNAME": "DATAENDDATE",
      "DATATYPE": "DATE",
      "LAYOUTID": "42"
    },
    {
      "COLUMNNAME": "EFFDATE",
      "DATATYPE": "DATE",
      "LAYOUTID": "42"
    },
    {
      "COLUMNNAME": "EMPLOYEECOUNT",
      "DATATYPE": "NUMBER",
      "LAYOUTID": "42"
    },
    {
      "COLUMNNAME": "ENRID",
      "DATATYPE": "VARCHAR2",
      "LAYOUTID": "42"
    },
    {
      "COLUMNNAME": "GENDER",
      "DATATYPE": "VARCHAR2",
      "LAYOUTID": "42"
    },
    {
      "COLUMNNAME": "HOMEPHONE",
      "DATATYPE": "VARCHAR2",
      "LAYOUTID": "42"
    },
    {
      "COLUMNNAME": "LOCATIONCODE",
      "DATATYPE": "VARCHAR2",
      "LAYOUTID": "42"
    },
    {
      "COLUMNNAME": "MEMBERCOUNT",
      "DATATYPE": "NUMBER",
      "LAYOUTID": "42"
    },
    {
      "COLUMNNAME": "MEMFIRSTNAME",
      "DATATYPE": "VARCHAR2",
      "LAYOUTID": "42"
    },
    {
      "COLUMNNAME": "MEMID",
      "DATATYPE": "VARCHAR2",
      "LAYOUTID": "42"
    },
    {
      "COLUMNNAME": "MEMLASTNAME",
      "DATATYPE": "VARCHAR2",
      "LAYOUTID": "42"
    },
    {
      "COLUMNNAME": "PARTTIMEFULLTIMEINDICATOR",
      "DATATYPE": "VARCHAR2",
      "LAYOUTID": "42"
    },
    {
      "COLUMNNAME": "PCPID",
      "DATATYPE": "VARCHAR2",
      "LAYOUTID": "42"
    },
    {
      "COLUMNNAME": "PCPNAME",
      "DATATYPE": "VARCHAR2",
      "LAYOUTID": "42"
    },
    {
      "COLUMNNAME": "PLANNAME",
      "DATATYPE": "VARCHAR2",
      "LAYOUTID": "42"
    },
    {
      "COLUMNNAME": "PLANTYPE",
      "DATATYPE": "VARCHAR2",
      "LAYOUTID": "42"
    },
    {
      "COLUMNNAME": "RECORDCOUNT",
      "DATATYPE": "NUMBER",
      "LAYOUTID": "42"
    },
    {
      "COLUMNNAME": "RELFLAG",
      "DATATYPE": "VARCHAR2",
      "LAYOUTID": "42"
    },
    {
      "COLUMNNAME": "STATE",
      "DATATYPE": "VARCHAR2",
      "LAYOUTID": "42"
    },
    {
      "COLUMNNAME": "STATUS",
      "DATATYPE": "VARCHAR2",
      "LAYOUTID": "42"
    },
    {
      "COLUMNNAME": "TERMDATE",
      "DATATYPE": "DATE",
      "LAYOUTID": "42"
    },
    {
      "COLUMNNAME": "WORKPHONE",
      "DATATYPE": "VARCHAR2",
      "LAYOUTID": "42"
    },
    {
      "COLUMNNAME": "ZIP",
      "DATATYPE": "VARCHAR2",
      "LAYOUTID": "42"
    }
  ]
}