{
  "_index": [
    "COLUMNNAME"
  ],
  "added": [
    {
      "COLUMNNAME": "bus_unit",
      "DATATYPE": "VARCHAR2",
      "LAYOUTID": "241"
    },
    {
      "COLUMNNAME": "clm_chk_dtc",
      "DATATYPE": "DATE",
      "LAYOUTID": "241"
    },
    {
      "COLUMNNAME": "clm_trans_typ",
      "DATATYPE": "VARCHAR2",
      "LAYOUTID": "241"
    },
    {
      "COLUMNNAME": "coverage_level",
      "DATATYPE": "VARCHAR2",
      "LAYOUTID": "241"
    },
    {
      "COLUMNNAME": "cust_def_f1",
      "DATATYPE": "VARCHAR2",
      "LAYOUTID": "241"
    },
    {
      "COLUMNNAME": "cust_def_f2",
      "DATATYPE": "VARCHAR2",
      "LAYOUTID": "241"
    },
    {
      "COLUMNNAME": "cust_def_f3",
      "DATATYPE": "VARCHAR2",
      "LAYOUTID": "241"
    },
    {
      "COLUMNNAME": "cust_def_f4",
      "DATATYPE": "VARCHAR2",
      "LAYOUTID": "241"
    },
    {
      "COLUMNNAME": "cust_def_f5",
      "DATATYPE": "VARCHAR2",
      "LAYOUTID": "241"
    },
    {
      "COLUMNNAME": "cust_def_f6",
      "DATATYPE": "VARCHAR2",
      "LAYOUTID": "241"
    },
    {
      "COLUMNNAME": "emp_stat",
      "DATATYPE": "VARCHAR2",
      "LAYOUTID": "241"
    },
    {
      "COLUMNNAME": "emp_typ",
      "DATATYPE": "VARCHAR2",
      "LAYOUTID": "241"
    },
    {
      "COLUMNNAME": "formulary_ind",
      "DATATYPE": "VARCHAR2",
      "LAYOUTID": "241"
    },
    {
      "COLUMNNAME": "ndc_drug_id",
      "DATATYPE": "VARCHAR2",
      "LAYOUTID": "241"
    },
    {
      "COLUMNNAME": "payer_id",
      "DATATYPE": "VARCHAR2",
      "LAYOUTID": "241"
    },
    {
      "COLUMNNAME": "person_dob",
      "DATATYPE": "DATE",
      "LAYOUTID": "241"
    },
    {
      "COLUMNNAME": "person_id",
      "DATATYPE": "VARCHAR2",
      "LAYOUTID": "241"
    },
    {
      "COLUMNNAME": "pharm_name",
      "DATATYPE": "VARCHAR2",
      "LAYOUTID": "241"
    },
    {
      "COLUMNNAME": "pharm_nbr",
      "DATATYPE": "VARCHAR2",
      "LAYOUTID": "241"
    },
    {
      "COLUMNNAME": "pharm_typ",
      "DATATYPE": "VARCHAR2",
      "LAYOUTID": "241"
    },
    {
      "COLUMNNAME": "pharm_zip",
      "DATATYPE": "VARCHAR2",
      "LAYOUTID": "241"
    },
    {
      "COLUMNNAME": "plan_code",
      "DATATYPE": "VARCHAR2",
      "LAYOUTID": "241"
    },
    {
      "COLUMNNAME": "prod_cd",
      "DATATYPE": "VARCHAR2",
      "LAYOUTID": "241"
    },
    {
      "COLUMNNAME": "prov_dea_nbr",
      "DATATYPE": "VARCHAR2",
      "LAYOUTID": "241"
    },
    {
      "COLUMNNAME": "raw_brand_genc_ind",
      "DATATYPE": "VARCHAR2",
      "LAYOUTID": "241"
    },
    {
      "COLUMNNAME": "relation",
      "DATATYPE": "VARCHAR2",
      "LAYOUTID": "241"
    },
    {
      "COLUMNNAME": "rx_admin_fee",
      "DATATYPE": "NUMBER",
      "LAYOUTID": "241"
    },
    {
      "COLUMNNAME": "rx_allow_chg_amt",
      "DATATYPE": "NUMBER",
      "LAYOUTID": "241"
    },
    {
      "COLUMNNAME": "rx_clm_nbr",
      "DATATYPE": "VARCHAR2",
      "LAYOUTID": "241"
    },
    {
      "COLUMNNAME": "rx_clm_nikey",
      "DATATYPE": "VARCHAR2",
      "LAYOUTID": "241"
    },
    {
      "COLUMNNAME": "rx_cob_amt",
      "DATATYPE": "NUMBER",
      "LAYOUTID": "241"
    },
    {
      "COLUMNNAME": "rx_coins_amt",
      "DATATYPE": "NUMBER",
      "LAYOUTID": "241"
    },
    {
      "COLUMNNAME": "rx_copay_amt",
      "DATATYPE": "NUMBER",
      "LAYOUTID": "241"
    },
    {
      "COLUMNNAME": "rx_days_supp",
      "DATATYPE": "VARCHAR2",
      "LAYOUTID": "241"
    },
    {
      "COLUMNNAME": "rx_deduct_amt",
      "DATATYPE": "NUMBER",
      "LAYOUTID": "241"
    },
    {
      "COLUMNNAME": "rx_disc_amt",
      "DATATYPE": "NUMBER",
      "LAYOUTID": "241"
    },
    {
      "COLUMNNAME": "rx_dispens_fee",
      "DATATYPE": "NUMBER",
      "LAYOUTID": "241"
    },
    {
      "COLUMNNAME": "rx_ingred_cost",
      "DATATYPE": "NUMBER",
      "LAYOUTID": "241"
    },
    {
      "COLUMNNAME": "rx_metric_qty",
      "DATATYPE": "NUMBER",
      "LAYOUTID": "241"
    },
    {
      "COLUMNNAME": "rx_nbr",
      "DATATYPE": "VARCHAR2",
      "LAYOUTID": "241"
    },
    {
      "COLUMNNAME": "rx_non_covd_chg_amt",
      "DATATYPE": "NUMBER",
      "LAYOUTID": "241"
    },
    {
      "COLUMNNAME": "rx_paid_amt",
      "DATATYPE": "NUMBER",
      "LAYOUTID": "241"
    },
    {
      "COLUMNNAME": "rx_sls_tax",
      "DATATYPE": "NUMBER",
      "LAYOUTID": "241"
    },
    {
      "COLUMNNAME": "rx_subm_chg_amt",
      "DATATYPE": "NUMBER",
      "LAYOUTID": "241"
    },
    {
      "COLUMNNAME": "serv_from_dtc",
      "DATATYPE": "DATE",
      "LAYOUTID": "241"
    },
    {
      "COLUMNNAME": "work_loc",
      "DATATYPE": "VARCHAR2",
      "LAYOUTID": "241"
    }
  ],
  "changed": [],
  "removed": [
    {
      "COLUMNNAME": "BCMBRNBR",
      "DATATYPE": "VARCHAR2",
      "LAYOUTID": "100"
    },
    {
      "COLUMNNAME": "BCTOS",
      "DATATYPE": "VARCHAR2",
      "LAYOUTID": "100"
    },
    {
      "COLUMNNAME": "CAPIND",
      "DATATYPE": "VARCHAR2",
      "LAYOUTID": "100"
    },
    {
      "COLUMNNAME": "CLAIMNBR",
      "DATATYPE": "VARCHAR2",
      "LAYOUTID": "100"
    },
    {
      "COLUMNNAME": "CLMCLS",
      "DATATYPE": "VARCHAR2",
      "LAYOUTID": "100"
    },
    {
      "COLUMNNAME": "CLMSYSID",
      "DATATYPE": "VARCHAR2",
      "LAYOUTID": "100"
    },
    {
      "COLUMNNAME": "COPAYAMT",
      "DATATYPE": "Number",
      "LAYOUTID": "100"
    },
    {
      "COLUMNNAME": "CURSUBID",
      "DATATYPE": "VARCHAR2",
      "LAYOUTID": "100"
    },
    {
      "COLUMNNAME": "DAW",
      "DATATYPE": "VARCHAR2",
      "LAYOUTID": "100"
    },
    {
      "COLUMNNAME": "DAYSUPLY",
      "DATATYPE": "VARCHAR2",
      "LAYOUTID": "100"
    },
    {
      "COLUMNNAME": "DEACLASSS",
      "DATATYPE": "VARCHAR2",
      "LAYOUTID": "100"
    },
    {
      "COLUMNNAME": "DEDUCT",
      "DATATYPE": "Number",
      "LAYOUTID": "100"
    },
    {
      "COLUMNNAME": "DRUGIND",
      "DATATYPE": "VARCHAR2",
      "LAYOUTID": "100"
    },
    {
      "COLUMNNAME": "EBYA",
      "DATATYPE": "VARCHAR2",
      "LAYOUTID": "100"
    },
    {
      "COLUMNNAME": "EMPREL",
      "DATATYPE": "VARCHAR2",
      "LAYOUTID": "100"
    },
    {
      "COLUMNNAME": "FIRSTNAM",
      "DATATYPE": "VARCHAR2",
      "LAYOUTID": "100"
    },
    {
      "COLUMNNAME": "FORMULRY",
      "DATATYPE": "VARCHAR2",
      "LAYOUTID": "100"
    },
    {
      "COLUMNNAME": "GENRCID",
      "DATATYPE": "VARCHAR2",
      "LAYOUTID": "100"
    },
    {
      "COLUMNNAME": "HCFACOCD",
      "DATATYPE": "VARCHAR2",
      "LAYOUTID": "100"
    },
    {
      "COLUMNNAME": "HEADCODE",
      "DATATYPE": "VARCHAR2",
      "LAYOUTID": "100"
    },
    {
      "COLUMNNAME": "LASTNAME",
      "DATATYPE": "VARCHAR2",
      "LAYOUTID": "100"
    },
    {
      "COLUMNNAME": "METRCQTY",
      "DATATYPE": "VARCHAR2",
      "LAYOUTID": "100"
    },
    {
      "COLUMNNAME": "NDC",
      "DATATYPE": "VARCHAR2",
      "LAYOUTID": "100"
    },
    {
      "COLUMNNAME": "NDCDES",
      "DATATYPE": "VARCHAR2",
      "LAYOUTID": "100"
    },
    {
      "COLUMNNAME": "NDCSTR",
      "DATATYPE": "VARCHAR2",
      "LAYOUTID": "100"
    },
    {
      "COLUMNNAME": "NETPAY",
      "DATATYPE": "Number",
      "LAYOUTID": "100"
    },
    {
      "COLUMNNAME": "NTWKPROD",
      "DATATYPE": "VARCHAR2",
      "LAYOUTID": "100"
    },
    {
      "COLUMNNAME": "ORDNPI",
      "DATATYPE": "VARCHAR2",
      "LAYOUTID": "100"
    },
    {
      "COLUMNNAME": "ORDRPHYS",
      "DATATYPE": "VARCHAR2",
      "LAYOUTID": "100"
    },
    {
      "COLUMNNAME": "PAID",
      "DATATYPE": "Number",
      "LAYOUTID": "100"
    },
    {
      "COLUMNNAME": "PATDOB",
      "DATATYPE": "Date",
      "LAYOUTID": "100"
    },
    {
      "COLUMNNAME": "PCPNBR",
      "DATATYPE": "VARCHAR2",
      "LAYOUTID": "100"
    },
    {
      "COLUMNNAME": "PCPNPI",
      "DATATYPE": "VARCHAR2",
      "LAYOUTID": "100"
    },
    {
      "COLUMNNAME": "PCPTNO",
      "DATATYPE": "VARCHAR2",
      "LAYOUTID": "100"
    },
    {
      "COLUMNNAME": "PDDATE",
      "DATATYPE": "Date",
      "LAYOUTID": "100"
    },
    {
      "COLUMNNAME": "PHARM_NPI",
      "DATATYPE": "VARCHAR2",
      "LAYOUTID": "100"
    },
    {
      "COLUMNNAME": "POS",
      "DATATYPE": "VARCHAR2",
      "LAYOUTID": "100"
    },
    {
      "COLUMNNAME": "PROCCODE",
      "DATATYPE": "VARCHAR2",
      "LAYOUTID": "100"
    },
    {
      "COLUMNNAME": "PROVID",
      "DATATYPE": "VARCHAR2",
      "LAYOUTID": "100"
    },
    {
      "COLUMNNAME": "PRVTYPECD",
      "DATATYPE": "VARCHAR2",
      "LAYOUTID": "100"
    },
    {
      "COLUMNNAME": "RATESTRU",
      "DATATYPE": "VARCHAR2",
      "LAYOUTID": "100"
    },
    {
      "COLUMNNAME": "REFCIRC",
      "DATATYPE": "VARCHAR2",
      "LAYOUTID": "100"
    },
    {
      "COLUMNNAME": "REFILL",
      "DATATYPE": "VARCHAR2",
      "LAYOUTID": "100"
    },
    {
      "COLUMNNAME": "RXORIGCD",
      "DATATYPE": "VARCHAR2",
      "LAYOUTID": "100"
    },
    {
      "COLUMNNAME": "SERVCODE",
      "DATATYPE": "VARCHAR2",
      "LAYOUTID": "100"
    },
    {
      "COLUMNNAME": "SEXCD",
      "DATATYPE": "VARCHAR2",
      "LAYOUTID": "100"
    },
    {
      "COLUMNNAME": "SUBMITCH",
      "DATATYPE": "VARCHAR2",
      "LAYOUTID": "100"
    },
    {
      "COLUMNNAME": "SVCDT",
      "DATATYPE": "Date",
      "LAYOUTID": "100"
    },
    {
      "COLUMNNAME": "THRPCLS",
      "DATATYPE": "VARCHAR2",
      "LAYOUTID": "100"
    },
    {
      "COLUMNNAME": "THRPGRP",
      "DATATYPE": "VARCHAR2",
      "LAYOUTID": "100"
    }
  ]
}